refactored_DC/__init__.py
refactored_DC/callbacks.py
refactored_DC/checkers.py
refactored_DC/data.py
refactored_DC/interfaceData.py
refactored_DC/metadata.py
refactored_DC/metrics.py
refactored_DC/settings.py
refactored_DC/test_checkers.py
refactored_DC/utils.py
refactored_DC/config/messages.properties
refactored_DC/config/settings.yaml
refactored_DC-0.0.4.dist-info/METADATA
refactored_DC-0.0.4.dist-info/WHEEL
refactored_DC-0.0.4.dist-info/top_level.txt
refactored_DC-0.0.4.dist-info/RECORD
