Metadata-Version: 2.1
Name: refactored-DC
Version: 0.0.4
Summary: Test package
Author: Poly
Author-email: <ghassendaoud99@gmail.com>
Keywords: python,cnn,test
Classifier: Development Status :: 1 - Planning
Classifier: Intended Audience :: Developers
Classifier: Programming Language :: Python :: 3
Classifier: Operating System :: Unix
Classifier: Operating System :: MacOS :: MacOS X
Classifier: Operating System :: Microsoft :: Windows
Requires-Dist: fastnumbers
